[
	{
		"id":"smallchest",
		"name":"Small Chest",
		"desc":"A small wooden chest.",
		"require":"state.gold>=50",
		"repeat":true,
		"cost":{
			"gold":50,
			"space":1
		},
		"mod":{
			"gold":{
				"max":75
			}
		}
	},
	{
		"id":"ironchest",
		"name":"Iron Chest",
		"desc":"Treasure chest.",
		"require":"state.gold>=150",
		"repeat":true,
		"cost":{
			"gold":200,
			"space":2
		},
		"mod":{
			"gold.max":200
		}
	},
	{
		"id":"vault",
		"desc":"A safe space for treasure.",
		"require":"state.space>=25",
		"repeat":true,
		"cost":{
			"gold":500,
			"space":10
		},
		"mod":{
			"gold.max":750,
			"gems.max":25
		}
	},
	{

		"id":"workbench",
		"name":"Workbench",
		"desc":"A small bench for crafting.",
		"cost":{
			"gold":25,
			"space":1
		},
		"mod":{
			"research.max":5
		}

	},
	{
		"id":"plant",
		"name":"Potted milkweed",
		"desc":"Brightens up the place",
		"cost":{
			"gold":25,
			"space":1
		},
		"mod":{
			"resarch.max":5
		}

	},
	{
		"id":"mortar",
		"name":"Mortar and Pestle",
		"desc":"Useful for grinding herbs & fine ingredients.",
		"require":"herbalism",
		"cost":{
			"gold":20,
			"space":1
		},
		"mod":{
			"research.max":5
		}
	},
	{
		"id":"birdcage",
		"desc":"Perfect for robins.",
		"cost":{
			"gold":25,
			"space":1
		},
		"mod":{
			"resarch.max":5
		}

	},
	{

		"id":"pedestal",
		"desc":"A pedestal for reading magic tomes.",
		"require":"neophyte",
		"cost":{
			"gold":50,
			"space":1
		},
		"mod":{
			"study.effect.research":0.1
		}

	},
	{
		"id":"sextant",
		"desc":"Measure the stars...",
		"require":"neophyte",
		"cost":{
			"gold":30,
			"research":50,
			"arcana":1,
			"space":2
		},
		"mod":{
			"arcana.max":1,
			"arcana.base":0.01
		}
	},
	{

		"id":"bookcase",
		"name":"Bookcase",
		"repeat":true,
		"desc":"A rough but sturdy bookcase.",
		"require":"state.codices>=10",
		"cost":{
			"gold":25,
			"space":2
		},
		"mod":{
			"codices":{
				"max":30
			}
		}

	},
	{
		"id":"casement",
		"name":"Casement Window",
		"desc":"A simple window to let in air and light.",
		"require":"state.space>10",
		"cost":{
			"gold":100,
			"space":1
		},
		"mod":{
			"light.base":0.01,
			"air.base":0.02
		}
	},
	{
		"id":"latticewindow",
		"name":"Lattice Window",
		"desc":"An elegant latticed portal.",
		"require":"state.space>=20",
		"cost":{
			"gold":300,
			"space":1
		},
		"mod":{
			"light.max":5,
			"air.max":10,
			"light.base":0.02,
			"air.base":0.05
		}
	},
	{

		"id":"brasscandelabra",
		"name":"brass candelabra",
		"desc":"Candle holder.",
		"require":"state.gold.max>75",
		"cost":{
			"space":1,
			"gold":100
		},
		"mod":{
			"candle.max":4
		}

	},
	{

		"id":"bonecandelabra",
		"name":"bone candelabra",
		"desc":"creepy",
		"require":"state.necromancer>0||state.witch>0",
		"cost":{
			"space":1,
			"bones":10,
			"research":50,
			"gold":50
		},
		"mod":{
			"candle.max":4,
			"shadow":{
				"base":0.04
			}
		}

	},
	{
		"id":"basin",
		"name":"basin",
		"desc":"Basin of water.",
		"require":"state.space>10",
		"cost":{
			"gold":50,
			"space":1
		},
		"mod":{
			"water.base":0.01,
			"water.max":10
		}
	},
	{
		"id":"brazier",
		"name":"Brazier",
		"desc":"Stand of burning hot coals.",
		"require":"state.space>10",
		"cost":{
			"gold":50,
			"space":1
		},
		"mod":{
			"fire.max":5,
			"fire.base":0.02
		}

	},
	{
		"id":"clepsydra",
		"desc":"Crude measure of time",
		"require":"adept",
		"cost":{
			"gold":100,
			"research":100,
			"space":1
		},
		"mod":{
			"tempus.max":5,
			"tempus.base":0.01,
			"water.base":0.01
		}

	},
	{
		"id":"fireplace",
		"name":"Fireplace",
		"desc":"A cozy place for cooking food and brewing potions.",
		"require":"state.space>=20",
		"cost":{
			"gold":50,
			"space":1
		},
		"mod":{
			"fire.base":0.1
		}

	},
	{
		"id":"fountain",
		"name":"fountain",
		"desc":"Water Fountain",
		"require":"state.space>20",
		"cost":{
			"gold":500,
			"space":5
		},
		"mod":{
			"water.base":0.5,
			"water.max":50
		}
	},
	{
		"id":"ossuary",
		"name":"Ossuary",
		"desc":"Receptacle for bones.",
		"require":"state.space>10",
		"cost":{
			"gold":20,
			"bones":5,
			"space":1
		},
		"mod":{
			"bones.max":10,
			"shadow.max":5
		}
	},
	{
		"id":"darkshrine",
		"name":"Dark Shrine",
		"desc":"A shrine to Evil.",
		"require":"state.space>10",
		"cost":{
			"gold":30,
			"bones":10,
			"shadow":10,
			"space":1
		},
		"mod":{
			"shadow.base":0.1,
			"shadow.max":10
		}
	},
	{
		"id":"ironcell",
		"name":"Iron Cell",
		"desc":"A simple, bare cell.",
		"require":"adept",
		"cost":{
			"gold":25,
			"space":5
		},
		"mod":{
			"shadow.max":1
		}

	},
	{
		"id":"shrine",
		"name":"Shrine",
		"desc":"A shrine to the divine forces.",
		"require":"state.space>10",
		"cost":{
			"gold":30,
			"gems":5,
			"light":10,
			"space":1
		},
		"mod":{
			"light.base":0.1,
			"light.max":10
		}
	},
	{
		"id":"bloodfountain",
		"name":"Blood Fountain",
		"desc":"Fountain of blood",
		"require":"state.space>20",
		"cost":{
			"gold":300,
			"shadow":20,
			"bones":20,
			"space":5
		},
		"mod":{
			"shadow.base":0.5,
			"shadow.max":50
		}
	},
	{
		"id":"studyroom",
		"name":"study",
		"desc":"A place for reading and research",
		"require":"state.codices>=100",
		"cost":{
			"gold":200,
			"research":100,
			"space":20
		},
		"mod":{
			"codices.max":100,
			"research.max":100,
			"research.base":0.05
		}

	},
	{
		"id":"library",
		"name":"Library",
		"desc":"",
		"require":"state.codices>=100",
		"cost":{
			"gold":500,
			"research":1000,
			"space":100
		},
		"mod":{
			"codices.max":1000,
			"research.max":100,
			"research.base":0.1
		}

	},
	{
		"id":"garden",
		"desc":"A small garden by your home.",
		"require":"witch",
		"cost":{
			"gold":100,
			"research":50,
			"space":20
		},
		"mod":{
			"herbs.base":1,
			"herbs.max":50,
			"nature.max":50,
			"nature.base":0.05
		}

	},
	{
		"id":"pond",
		"name":"pond",
		"desc":"Pond",
		"require":"state.space>50",
		"cost":{
			"gold":500,
			"space":25
		},
		"mod":{
			"water.base":0.1,
			"nature.base":0.1,
			"nature.max":50,
			"water.max":100
		}
	},
	{

		"id":"workshop",
		"name":"Workshop",
		"desc":"A space suitable for crafting items.",
		"require":"state.space>100",
		"cost":{
			"space":50,
			"gold":500,
			"research":25
		},
		"mod":{
			"research.max":10
		}

	}

]